kolsol/__init__.py
kolsol/base/__init__.py
kolsol/base/base_solver.py
kolsol/numpy/__init__.py
kolsol/numpy/solver.py
kolsol/torch/__init__.py
kolsol/torch/solver.py
kolsol/utils/__init__.py
kolsol/utils/enums.py
kolsol/utils/integrate.py
kolsol/utils/types.py
kolsol-1.0.1.dist-info/LICENSE
kolsol-1.0.1.dist-info/WHEEL
kolsol-1.0.1.dist-info/METADATA
kolsol-1.0.1.dist-info/RECORD
