Metadata-Version: 2.1
Name: kolsol
Version: 1.0.1
Summary: Pseudospectral Kolmogorov Flow Solver
Author-email: Daniel Kelshaw <daniel.j.kelshaw@gmail.com>
Requires-Python: >=3.8.10
Classifier: License :: OSI Approved :: MIT License
Requires-Dist: numpy
Requires-Dist: einops
Requires-Dist: opt_einsum
Requires-Dist: torch
Requires-Dist: tqdm
Requires-Dist: h5py
Requires-Dist: mypy ; extra == "dev"
Requires-Dist: pylint ; extra == "dev"
Requires-Dist: pytest ; extra == "dev"
Project-URL: Home, https://github.com/magrilab/kolsol
Provides-Extra: dev
